ffm/__init__.py
ffm/embeddings/__init__.py
ffm/embeddings/base.py
ffm/langchain/__init__.py
ffm/langchain/callbacks/__init__.py
ffm/langchain/callbacks/ffm_callbacks.py
ffm/langchain/callbacks/manager.py
ffm/langchain/language_models/__init__.py
ffm/langchain/language_models/ffm.py
ffm/openai/__init__.py
ffm/openai/lib/__init__.py
ffm/openai/lib/ffm.py
ffm/openai/lib/streaming.py
ffm/openai/resources/__init__.py
ffm/openai/resources/completions.py
ffm/openai/resources/chat/__init__.py
ffm/openai/resources/chat/chat.py
ffm/openai/resources/chat/completions.py
ffm/openai/types/__init__.py
ffm/openai/types/chat/__init__.py
ffm/openai/types/chat/chat_complection_chunk.py
ffm/openai/types/chat/chat_completion.py
tests/__init__.py
tests/test_ffm_embeddings.py
unofficial_ffm_openai-0.2.1.dist-info/LICENSE
unofficial_ffm_openai-0.2.1.dist-info/METADATA
unofficial_ffm_openai-0.2.1.dist-info/WHEEL
unofficial_ffm_openai-0.2.1.dist-info/top_level.txt
unofficial_ffm_openai-0.2.1.dist-info/RECORD
