Metadata-Version: 2.1
Name: unofficial_ffm_openai
Version: 0.2.1
Summary: An unofficial Formosa Foundation Model API client implementation compatible with LangChain and OpenAI
Author-email: derekhsu <derekhsu@hotmail.com>
License: MIT License
Project-URL: Homepage, https://github.com/derekhsu/unoffcial_ffm_openai_client
Classifier: Programming Language :: Python :: 3
Classifier: License :: OSI Approved :: MIT License
Classifier: Operating System :: OS Independent
Requires-Python: >=3.10
License-File: LICENSE
Requires-Dist: langchain-openai
Requires-Dist: langchain-core
Requires-Dist: langchain
Requires-Dist: openai >=1.23.3
